ut_htx/__init__.py
ut_htx/__version__.py
ut_htx/httpx_.py
ut_htx/py.typed
ut_htx/utils.py
ut_htx/data/__init__.py
ut_htx/data/srr.yml
ut_htx-2.0.0.20251020.dist-info/licenses/LICENSE.txt
ut_htx-2.0.0.20251020.dist-info/METADATA
ut_htx-2.0.0.20251020.dist-info/WHEEL
ut_htx-2.0.0.20251020.dist-info/top_level.txt
ut_htx-2.0.0.20251020.dist-info/RECORD
